{
  "kind": "collectionType",
  "collectionName": "events",
  "info": {
    "singularName": "event",
    "pluralName": "events",
    "displayName": "Events"
  },
  "options": {
    "draftAndPublish": true
  },
  "pluginOptions": {},
  "attributes": {
    "name": {
      "type": "string"
    },
    "venue": {
      "type": "string"
    },
    "address": {
      "type": "string"
    },
    "date": {
      "type": "datetime"
    },
    "slug": {
      "type": "uid",
      "targetField": "name"
    },
    "performers": {
      "type": "string"
    },
    "description": {
      "type": "text"
    },
    "image": {
      "allowedTypes": [
        "images",
        "files",
        "videos",
        "audios"
      ],
      "type": "media",
      "multiple": true
    },
    "user": {
      "type": "relation",
      "relation": "manyToOne",
      "target": "plugin::users-permissions.user",
      "inversedBy": "events"
    }
  }
}
